{

  "code": "ES",
  "commands_config": [
    {
      "name": "help",
      "description": "Long Description here",
      "usage": "Long usage here"
    }
  ],
  "bot_messages": [
    {
      "id": 1,
      "name": "Permissos Insuficientes",
      "value": "No tienes suficientes permisos para hacer eso!"
    },
    {
      "id": 2,
      "name": "Error",
      "value": "Porfabor menciona a un usuario valido."
    },
    {
      "id": 3,
      "name": "Error",
      "value": "Porfabor menciona a un rol valido."
    },
    {
      "id": 4,
      "name": "Error",
      "value": "Ha ocurrido un error: {{error}}"
    },
    {
      "id": 5,
      "name": "Éxito!",
      "value": "El rol {{role}} ha sido añadido a {{user}}."
    },
    {
      "id": 6,
      "name": "Error",
      "value": "Ese formato de archivo no está permitido."
    },
    {
      "id": 7,
      "name": "Éxito!",
      "value": "He creado el emoji {{emoji}}."
    },
    {
      "id": 8,
      "name": "Éxito!",
      "value": "Todos los canales [{{channels_size}}] han sido bloqueados."
    },
    {
      "id": 9,
      "name": "Success!",
      "value": "{{channel}} has been locked down!"
    },
    {
      "id": 10,
      "name": "Success!",
      "value": "Emoji {{emoji}} has been deleted successfully!"
    },
    {
      "id": 11,
      "name": "Error",
      "value": "Please mention a valid emoji."
    },
    {
      "id": 12,
      "name": "Error",
      "value": "Emoji not found!"
    },
    {
      "id": 13,
      "name": "Error",
      "value": "This user hasn't got that role."
    },
    {
      "id": 14,
      "name": "Success!",
      "value": "{{role}} has been removed from {{user}}"
    },
    {
      "id": 15,
      "name": "",
      "value": "This channel is not nsfw!"
    },
    {
      "id": 16,
      "name": "Error",
      "value": "A prefix can't be longer than 10 characters."
    },
    {
      "id": 17,
      "name": "Success!",
      "value": "Prefix for {{guild}} has been changed to {{prefix}}."
    },
    {
      "id": 18,
      "name": "Error",
      "value": "Please mention a prefix."
    },
    {
      "id": 19,
      "name": "Success!",
      "value": "BotLogs channel has now been changed to {{channel}}."
    },
    {
      "id": 20,
      "name": "Error",
      "value": "This channel cannot be set as botlogs."
    },
    {
      "id": 21,
      "name": "Success!",
      "value": "Initial role has been changed to <@&{{role_id}}>."
    },
    {
      "id": 22,
      "name": "Success!",
      "value": "The leave channel has been updated to {{channel}}"
    },
    {
      "id": 23,
      "name": "Success!",
      "value": "The leave message has been updated to {{message}} \n Please keep in mind that {user} replaces the user and {totalme} replaces the total members!"
    },
    {
      "id": 24,
      "name": "Error",
      "value": "Please mention a valid message."
    },
    {
      "id": 25,
      "name": "Error",
      "value": "Please specify a valid module."
    },
    {
      "id": 26,
      "name": "Error",
      "value": "Please give a value."
    },
    {
      "id": 27,
      "name": "Success!",
      "value": "Module {{module}} has been set to {{value}}."
    },
    {
      "id": 28,
      "name": "Success!",
      "value": "The welcome channel has been updated to {{channel}}"
    },
    {
      "id": 29,
      "name": "Success!",
      "value": "The welcome channel has been updated to {{channel}}"
    },
    {
      "id": 30,
      "name": "Success!",
      "value": "The welcome message has been updated to {{message}} \n Please keep in mind that {user} replaces the user and {totalme} replaces the total members!"
    },
    {
      "id": 31,
      "name": "Success!",
      "value": "{{channel}} has been unlocked."
    },
    {
      "id": 32,
      "name": "Success!",
      "value": "All channels have been unlocked!"
    },
    {
      "id": 33,
      "name": "",
      "value": "Claimed your daily ${{daily}}"
    },
    {
      "id": 34,
      "name": "",
      "value": "You must wait ${{time}} before claiming your reward again!"
    },
    {
      "id": 35,
      "name": "You don't have enough money to do that!",
      "value": "You need {{money}}"
    },
    {
      "id": 36,
      "name": "Success!",
      "value": "${{money}} has been deposited in your bank account (${{tax}} tax)."
    },
    {
      "id": 37,
      "name": "Error",
      "value": "Mention a valid amount."
    },
    {
      "id": 38,
      "name": "",
      "value": "Claimed your hourly ${{hourly}}"
    },
    {
      "id": 39,
      "name": "",
      "value": "Claimed your weekly ${{weekly}}"
    },
    {
      "id": 40,
      "name": "Pocket Money: ${{money}}",
      "value": "Bank: %${{bank}}"
    },
    {
      "id": 41,
      "name": "Success!",
      "value": "{{payer}} payed {{user}} ${{money}}"
    },
    {
      "id": 42,
      "name": "Success!",
      "value": "${{money}} has been withdrawedoff your bank account (${{tax}} tax)."
    },
    {
      "id": 43,
      "name": "Error",
      "value": "Please don't convert messages longer than 14 characters."
    },
    {
      "id": 44,
      "name": "",
      "value": "Requested by {{user}}"
    },
    {
      "id": 45,
      "name": "",
      "value": "Did you know?"
    },
    {
      "id": 46,
      "name": "",
      "value": "Example"
    },
    {
      "id": 47,
      "name": "",
      "value": "Upvotes"
    },
    {
      "id": 48,
      "name": "",
      "value": "Downvotes"
    },
    {
      "id": 49,
      "name": "",
      "value": "Author"
    },
    {
      "id": 50,
      "name": "Error",
      "value": "Please input a region!"
    },
    {
      "id": 51,
      "name": "",
      "value": "Lowest Temperature"
    },
    {
      "id": 52,
      "name": "",
      "value": "Highest Temperature"
    },
    {
      "id": 53,
      "name": "",
      "value": "Sky Appearence"
    },
    {
      "id": 54,
      "name": "",
      "value": "Precipitation chance"
    },
    {
      "id": 55,
      "name": "",
      "value": "Temperature"
    },
    {
      "id": 56,
      "name": "",
      "value": "Wind Speed"
    },
    {
      "id": 57,
      "name": "",
      "value": "Humidity"
    },
    {
      "id": 58,
      "name": "",
      "value": "Downvotes"
    },
    {
      "id": 59,
      "name": "",
      "value": "Info About TodoBot"
    },
    {
      "id": 60,
      "name": "",
      "value": "Developers"
    },
    {
      "id": 61,
      "name": "",
      "value": "Website"
    },
    {
      "id": 62,
      "name": "",
      "value": "Library"
    },
    {
      "id": 63,
      "name": "",
      "value": "NodeJS version"
    },
    {
      "id": 64,
      "name": "",
      "value": "Commands"
    },
    {
      "id": 65,
      "name": "",
      "value": "Guilds"
    },
    {
      "id": 66,
      "name": "",
      "value": "Users"
    },
    {
      "id": 67,
      "name": "",
      "value": "Hosting Provided by todo56.dev"
    },
    {
      "id": 68,
      "name": "",
      "value": "Stats for command"
    },
    {
      "id": 69,
      "name": "",
      "value": "Number of Uses"
    },
    {
      "id": 70,
      "name": "",
      "value": "Description"
    },
    {
      "id": 71,
      "name": "",
      "value": "Help for command {{command}}"
    },
    {
      "id": 72,
      "name": "",
      "value": "Usage"
    },
    {
      "id": 73,
      "name": "",
      "value": "Aliases"
    },
    {
      "id": 74,
      "name": "Not found",
      "value": "The command {{command}} has not been found."
    },
    {
      "id": 75,
      "name": "",
      "value": "Command Stats"
    },
    {
      "id": 76,
      "name": "",
      "value": "These are our 10 most used commands"
    },
    {
      "id": 77,
      "name": "",
      "value": "Thanks for adding me to your server :D"
    },
    {
      "id": 78,
      "name": "",
      "value": "These are all my categories! [{{category_size}}]"
    },
    {
      "id": 79,
      "name": "Not found",
      "value": "The command or alias {{command}} has not been found."
    },
    {
      "id": 80,
      "name": "Bot latency is:",
      "value": "API latency is:"
    },
    {
      "id": 81,
      "name": "Error",
      "value": "This user is not playing anything."
    },
    {
      "id": 82,
      "name": "",
      "value": "Name"
    },
    {
      "id": 83,
      "name": "",
      "value": "Mention"
    },
    {
      "id": 84,
      "name": "",
      "value": "Color"
    },
    {
      "id": 85,
      "name": "",
      "value": "Members"
    },
    {
      "id": 86,
      "name": "",
      "value": "Position"
    },
    {
      "id": 87,
      "name": "",
      "value": "Hoisted"
    },
    {
      "id": 88,
      "name": "",
      "value": "Mentionable"
    },
    {
      "id": 89,
      "name": "",
      "value": "Managed"
    },
    {
      "id": 90,
      "name": "",
      "value": "Key Permissions"
    },
    {
      "id": 91,
      "name": "Success!",
      "value": "{{user}} has been banned successfully!"
    },
    {
      "id": 92,
      "name": "",
      "value": "Users banned"
    },
    {
      "id": 93,
      "name": "Success!",
      "value": "Warnings for {{user}} have been deleted. Total of {{num}}"
    },
    {
      "id": 94,
      "name": "Error",
      "value": "Please mention a valid id."
    },
    {
      "id": 95,
      "name": "Success!",
      "value": "Warnings with id {{id}} has been deleted."
    },
    {
      "id": 96,
      "name": "Error",
      "value": "I don't have permission to do that!"
    },
    {
      "id": 97,
      "name": "Success!",
      "value": "{{user}} has been kicked successfully."
    },
    {
      "id": 98,
      "name": "Success!",
      "value": "{{user}} has been muted successfully."
    },
    {
      "id": 99,
      "name": "Success!",
      "value": "I've purged {{num}} messages successfully."
    },
    {
      "id": 100,
      "name": "Success!",
      "value": "Mention an id please. You can get all banned ids using the command bans."
    },
    {
      "id": 101,
      "name": "Success!",
      "value": "{{user}} has been unmuted successfully."
    },
    {
      "id": 102,
      "name": "Success!",
      "value": "{{user}} has been warned successfully."
    },
    {
      "id": 103,
      "name": "Not found",
      "value": "No warnings could be found for {{user}}"
    },
    {
      "id": 104,
      "name": "Error",
      "value": "Mention a valid url or attach a file."
    }
  ]
}
